gradesystemprotyai/__init__.py
gradesystemprotyai/tyaigradesystepro142.py
gradesystemprotyai-1.4.4.dist-info/METADATA
gradesystemprotyai-1.4.4.dist-info/WHEEL
gradesystemprotyai-1.4.4.dist-info/top_level.txt
gradesystemprotyai-1.4.4.dist-info/RECORD
