Metadata-Version: 2.1
Name: gradesystemprotyai
Version: 1.4.4
Summary: TYAI Web Update Package
Author: Yihuan
Author-email: ivan17.lai@gmail.com
Requires-Dist: selenium
Requires-Dist: beautifulsoup4
Requires-Dist: keras
Requires-Dist: opencv-python
Requires-Dist: Pillow
Requires-Dist: tensorflow
